bauh/__init__.py
bauh/app.py
bauh/app_args.py
bauh/context.py
bauh/manage.py
bauh/stylesheet.py
bauh/tray.py
bauh/api/__init__.py
bauh/api/exception.py
bauh/api/http.py
bauh/api/paths.py
bauh/api/user.py
bauh/api/abstract/__init__.py
bauh/api/abstract/cache.py
bauh/api/abstract/context.py
bauh/api/abstract/controller.py
bauh/api/abstract/disk.py
bauh/api/abstract/download.py
bauh/api/abstract/handler.py
bauh/api/abstract/model.py
bauh/api/abstract/view.py
bauh/cli/__init__.py
bauh/cli/app.py
bauh/cli/cli_args.py
bauh/cli/controller.py
bauh/commons/__init__.py
bauh/commons/boot.py
bauh/commons/category.py
bauh/commons/config.py
bauh/commons/custom_types.py
bauh/commons/html.py
bauh/commons/internet.py
bauh/commons/regex.py
bauh/commons/resource.py
bauh/commons/singleton.py
bauh/commons/suggestions.py
bauh/commons/system.py
bauh/commons/util.py
bauh/commons/version_util.py
bauh/commons/view_utils.py
bauh/desktop/bauh.desktop
bauh/desktop/bauh_tray.desktop
bauh/gems/__init__.py
bauh/gems/appimage/__init__.py
bauh/gems/appimage/config.py
bauh/gems/appimage/controller.py
bauh/gems/appimage/model.py
bauh/gems/appimage/query.py
bauh/gems/appimage/util.py
bauh/gems/appimage/worker.py
bauh/gems/appimage/resources/__init__.py
bauh/gems/appimage/resources/img/__init__.py
bauh/gems/appimage/resources/img/appimage.svg
bauh/gems/appimage/resources/img/refresh.svg
bauh/gems/appimage/resources/locale/__init__.py
bauh/gems/appimage/resources/locale/ca
bauh/gems/appimage/resources/locale/de
bauh/gems/appimage/resources/locale/en
bauh/gems/appimage/resources/locale/es
bauh/gems/appimage/resources/locale/fr
bauh/gems/appimage/resources/locale/it
bauh/gems/appimage/resources/locale/pt
bauh/gems/appimage/resources/locale/ru
bauh/gems/appimage/resources/locale/tr
bauh/gems/arch/__init__.py
bauh/gems/arch/aur.py
bauh/gems/arch/config.py
bauh/gems/arch/confirmation.py
bauh/gems/arch/controller.py
bauh/gems/arch/cpu_manager.py
bauh/gems/arch/database.py
bauh/gems/arch/dependencies.py
bauh-0.10.7.dist-info/LICENSE
bauh-0.10.7.dist-info/METADATA
bauh-0.10.7.dist-info/WHEEL
bauh-0.10.7.dist-info/entry_points.txt
bauh-0.10.7.dist-info/top_level.txt
bauh-0.10.7.dist-info/RECORD
