Metadata-Version: 2.1
Name: bauh
Version: 0.10.7
Summary: Graphical interface to manage Linux applications (AppImage, Arch / AUR, Flatpak, Snap and Web)
Author-email: Vinicius Moreira <vinicius_fmoreira@hotmail.com>
License: Copyright (c) 2019 Vinícius Moreira
Project-URL: Repository, https://github.com/vinifmor/bauh
Classifier: Topic :: Utilities
Classifier: Programming Language :: Python
Classifier: Programming Language :: Python :: 3.6
Classifier: Programming Language :: Python :: 3.7
Classifier: Programming Language :: Python :: 3.8
Classifier: Programming Language :: Python :: 3.9
Classifier: Programming Language :: Python :: 3.10
Classifier: Programming Language :: Python :: 3.11
Requires-Python: >=3.6
License-File: LICENSE
Requires-Dist: pyqt5 >=5.12
Requires-Dist: requests >=2.18
Requires-Dist: colorama >=0.3.8
Requires-Dist: pyyaml >=3.13
Requires-Dist: python-dateutil >=2.7
Provides-Extra: web
Requires-Dist: lxml >=4.2.0 ; extra == 'web'
Requires-Dist: beautifulsoup4 >=4.7.0 ; extra == 'web'
